README.md
setup.cfg
setup.py
bin/litctl
bin/litdev
lit/__init__.py
lit/color.py
lit/commands.py
lit/controller.py
lit/device.py
lit/effect.py
lit/error.py
lit/history.py
lit/lit.py
lit/litd.py
lit/section.py
lit/colors/__init__.py
lit/colors/cycle.py
lit/colors/random.py
lit/colors/static.py
lit/config/colors.json
lit/config/presets.json
lit/config/ranges.json
lit/config/speeds.json
lit/effects/__init__.py
lit/effects/_template.py
lit/effects/chase.py
lit/effects/christmas.py
lit/effects/christmas_lights.py
lit/effects/collision.py
lit/effects/disco.py
lit/effects/drip.py
lit/effects/fade.py
lit/effects/fireflies.py
lit/effects/heart.py
lit/effects/nexus.py
lit/effects/off.py
lit/effects/on.py
lit/effects/police.py
lit/effects/pride.py
lit/effects/rave.py
lit/effects/strobe.py
lit/effects/throb.py
lit/effects/twinkle.py
lit_core.egg-info/PKG-INFO
lit_core.egg-info/SOURCES.txt
lit_core.egg-info/dependency_links.txt
lit_core.egg-info/entry_points.txt
lit_core.egg-info/requires.txt
lit_core.egg-info/top_level.txt