Metadata-Version: 1.2
Name: lit-core
Version: 0.0.4
Summary: Lit Ilumination Technology
Home-page: https://github.com/lit-illumination-technology/lit_core
Author: Nick Pesce
Author-email: nickpesce22@gmail.com
License: UNKNOWN
Platform: UNKNOWN
Classifier: License :: OSI Approved :: GNU General Public License v3 (GPLv3)
Classifier: Operating System :: POSIX :: Linux
Classifier: Development Status :: 3 - Alpha
Classifier: Programming Language :: Python :: 3
Classifier: Topic :: Home Automation
Requires-Python: >=3.5
